fossil_mastodon/__init__.py
fossil_mastodon/algorithm.py
fossil_mastodon/app/index.js
fossil_mastodon/app/static/htmx.js
fossil_mastodon/app/static/logo-light.svg
fossil_mastodon/app/static/page.js
fossil_mastodon/app/static/style.css
fossil_mastodon/app/static/work-in-progress.gif
fossil_mastodon/app/templates/bad_plugin.html
fossil_mastodon/app/templates/base/admin.html
fossil_mastodon/app/templates/base/page.html
fossil_mastodon/app/templates/index.html
fossil_mastodon/app/templates/no_algorithm.html
fossil_mastodon/app/templates/settings.html
fossil_mastodon/app/templates/toot.html
fossil_mastodon/app/templates/toot_clusters.html
fossil_mastodon/app/templates/toot_list.html
fossil_mastodon/config.py
fossil_mastodon/core.py
fossil_mastodon/migrations.py
fossil_mastodon/plugin_impl/__init__.py
fossil_mastodon/plugin_impl/toot_debug.py
fossil_mastodon/plugin_impl/topic_cluster.py
fossil_mastodon/plugins.py
fossil_mastodon/science.py
fossil_mastodon/server.py
fossil_mastodon/ui.py
index.html
fossil_mastodon-0.3.0.dist-info/METADATA
fossil_mastodon-0.3.0.dist-info/WHEEL
fossil_mastodon-0.3.0.dist-info/entry_points.txt
fossil_mastodon-0.3.0.dist-info/RECORD
